{
  "id": "Siesta-4217",
  "vrboId": "4135262",
  "title": "Right At Home-Midland Cowboy Siesta Corner Lot",
  "tagline": "Western-themed corner lot home for a relaxing stay",
  "propertyType": "Entire home",
  "location": {
    "city": "Midland",
    "state": "TX",
    "address": "4217 Siesta",
    "coordinates": null
  },
  "specs": {
    "bedrooms": 3,
    "bathrooms": 2,
    "sleeps": 6
  },
  "rooms": [
    {
      "name": "Bedroom 1",
      "beds": "1 King bed"
    },
    {
      "name": "Bedroom 2",
      "beds": "1 Queen bed"
    },
    {
      "name": "Bedroom 3",
      "beds": "2 Twin beds"
    }
  ],
  "spaces": [
    "Kitchen",
    "Living room",
    "Separate dining area",
    "Corner lot yard"
  ],
  "amenities": {
    "topFamilyFriendly": [
      "Kitchen",
      "Microwave",
      "Living/dining area"
    ],
    "popular": [
      "Corner lot",
      "Washing machine",
      "Dryer",
      "Pet-friendly",
      "Free Wi-Fi",
      "Air-conditioning",
      "Outdoor space",
      "Parking available",
      "Barbecue"
    ],
    "essentials": [
      "Wireless internet",
      "Free wifi",
      "Wifi speed: 500+ Mbps",
      "Towels provided",
      "Linens provided",
      "Air conditioning",
      "Hair dryer",
      "Shampoo",
      "Toilet paper",
      "Paper towels",
      "Basic soaps",
      "Iron & board",
      "Heating"
    ],
    "kitchen": [
      "Kitchen",
      "Refrigerator",
      "Dishwasher",
      "Microwave",
      "Stove",
      "Oven",
      "Grill",
      "Dishes & utensils",
      "Dining table",
      "Coffee maker",
      "Toaster"
    ],
    "outside": [
      "Outdoor furniture",
      "Corner lot yard"
    ],
    "pets": [
      "Pet friendly",
      "Up to 23 kg per pet"
    ],
    "entertainment": [
      "Television",
      "Smart TV"
    ],
    "laundry": [
      "Washing machine",
      "Dryer"
    ],
    "parking": [
      "Parking",
      "Driveway"
    ]
  },
  "houseRules": {
    "checkIn": "After 3:00 pm",
    "checkOut": "Before 11:00 am",
    "children": "Allowed",
    "events": "No events allowed",
    "pets": "Allowed (up to 23 kg per pet)",
    "smoking": "No smoking"
  },
  "importantInfo": [
    "Minimum age to rent: 25"
  ],
  "reviews": {
    "rating": 9,
    "count": 0,
    "breakdown": {}
  },
  "host": {
    "name": "STEVEN M PALMA",
    "isPremier": true,
    "languages": [
      "English"
    ]
  },
  "images": {
    "main": "main.webp",
    "count": 16
  },
  "serviceFees": {
    "cleaningFee": 150,
    "deepCleanFee": 300,
    "poolServiceFee": 0,
    "lawnServiceFee": 75
  },
  "waiverRequirements": {
    "pool": false,
    "hotTub": true,
    "firePit": false,
    "general": true
  },
  "hasPool": false,
  "hasHotTub": true,
  "hasFirePit": false
}
